fastapi_hypermodel/__init__.py
fastapi_hypermodel/base/__init__.py
fastapi_hypermodel/base/hypermodel.py
fastapi_hypermodel/base/url_type.py
fastapi_hypermodel/base/utils.py
fastapi_hypermodel/hal/__init__.py
fastapi_hypermodel/hal/hal_hypermodel.py
fastapi_hypermodel/hal/hal_response.py
fastapi_hypermodel/py.typed
fastapi_hypermodel/siren/__init__.py
fastapi_hypermodel/siren/siren_action.py
fastapi_hypermodel/siren/siren_base.py
fastapi_hypermodel/siren/siren_field.py
fastapi_hypermodel/siren/siren_hypermodel.py
fastapi_hypermodel/siren/siren_link.py
fastapi_hypermodel/siren/siren_response.py
fastapi_hypermodel/siren/siren_schema.py
fastapi_hypermodel/url_for/__init__.py
fastapi_hypermodel/url_for/url_for.py
fastapi_hypermodel-2.2.0.dist-info/LICENSE
fastapi_hypermodel-2.2.0.dist-info/METADATA
fastapi_hypermodel-2.2.0.dist-info/WHEEL
fastapi_hypermodel-2.2.0.dist-info/RECORD
