Metadata-Version: 2.3
Name: fastapi-hypermodel
Version: 2.2.0
Summary: A FastAPI + Pydantic extension for simplifying hypermedia-driven API development.
Home-page: https://github.com/jtc42/fastapi-hypermodel
License: MIT
Author: Joel Collins
Author-email: joel@jtcollins.net
Requires-Python: >=3.9,<4
Classifier: License :: OSI Approved :: MIT License
Classifier: Programming Language :: Python :: 3
Classifier: Programming Language :: Python :: 3.9
Classifier: Programming Language :: Python :: 3.10
Classifier: Programming Language :: Python :: 3.11
Classifier: Programming Language :: Python :: 3.12
Classifier: Programming Language :: Python :: 3.13
Requires-Dist: fastapi (>=0.115.2,<1)
Requires-Dist: frozendict (>=2.0.2,<3)
Requires-Dist: jsonref (>=0.1,<2)
Requires-Dist: jsonschema (>=2.0.0,<5)
Requires-Dist: pydantic (>=2.8.0,<3.0)
Requires-Dist: starlette (>=0.37.2,<1)
Requires-Dist: typing_extensions (>=4.12.2,<5)
Project-URL: Repository, https://github.com/jtc42/fastapi-hypermodel
